dotclaude/__init__.py
dotclaude/__main__.py
dotclaude/cli.py
dotclaude/commands/__init__.py
dotclaude/commands/command_utils.py
dotclaude/core/__init__.py
dotclaude/core/config_manager.py
dotclaude/core/git_manager.py
dotclaude/core/strategy_factory.py
dotclaude/core/sync_engine.py
dotclaude/core/sync_strategies.py
dotclaude/core/sync_utils.py
dotclaude/domain/constants.py
dotclaude/domain/entities/__init__.py
dotclaude/domain/entities/agent.py
dotclaude/domain/entities/repository.py
dotclaude/domain/entities/sync_item.py
dotclaude/domain/exceptions/__init__.py
dotclaude/domain/exceptions/base.py
dotclaude/domain/exceptions/config.py
dotclaude/domain/exceptions/git.py
dotclaude/domain/exceptions/security.py
dotclaude/domain/exceptions/sync.py
dotclaude/domain/value_objects/__init__.py
dotclaude/domain/value_objects/agent_info.py
dotclaude/domain/value_objects/config_key.py
dotclaude/domain/value_objects/sync_options.py
dotclaude/domain/value_objects/sync_result.py
dotclaude/infrastructure/__init__.py
dotclaude/infrastructure/error_handling/__init__.py
dotclaude/infrastructure/error_handling/error_boundary.py
dotclaude/infrastructure/error_handling/error_formatter.py
dotclaude/infrastructure/error_handling/error_recovery.py
dotclaude/infrastructure/services/__init__.py
dotclaude/infrastructure/services/console_service.py
dotclaude/infrastructure/services/interactive_service.py
dotclaude/infrastructure/services/local_agents_service.py
dotclaude/infrastructure/services/security_service.py
dotclaude/infrastructure/services/validation_service.py
dotclaude/infrastructure/validators/__init__.py
dotclaude/infrastructure/validators/agent_validator.py
dotclaude/infrastructure/validators/branch_validator.py
dotclaude/infrastructure/validators/config_validator.py
dotclaude/infrastructure/validators/path_validator.py
dotclaude/infrastructure/validators/url_validator.py
dotclaude/interfaces/__init__.py
dotclaude/interfaces/repositories.py
dotclaude/interfaces/services.py
dotclaude-0.1.1.dist-info/METADATA
dotclaude-0.1.1.dist-info/WHEEL
dotclaude-0.1.1.dist-info/entry_points.txt
dotclaude-0.1.1.dist-info/RECORD
