Metadata-Version: 2.4
Name: dotclaude
Version: 0.1.1
Summary: Modern CLI tool for managing Claude Code configuration
Project-URL: Homepage, https://github.com/FradSer/dotclaude
Project-URL: Repository, https://github.com/FradSer/dotclaude
Project-URL: Documentation, https://github.com/FradSer/dotclaude
Project-URL: Bug Tracker, https://github.com/FradSer/dotclaude/issues
Author-email: FradSer <frad@frad.io>
License: MIT
Keywords: agents,ai,claude,configuration,sync
Classifier: Development Status :: 4 - Beta
Classifier: Intended Audience :: Developers
Classifier: License :: OSI Approved :: MIT License
Classifier: Operating System :: OS Independent
Classifier: Programming Language :: Python :: 3
Classifier: Programming Language :: Python :: 3.9
Classifier: Programming Language :: Python :: 3.10
Classifier: Programming Language :: Python :: 3.11
Classifier: Programming Language :: Python :: 3.12
Classifier: Topic :: Software Development
Classifier: Topic :: Utilities
Requires-Python: >=3.9
Requires-Dist: aiofiles<24.0.0,>=23.0.0
Requires-Dist: click<9.0.0,>=8.1.7
Requires-Dist: gitpython<4.0.0,>=3.1.40
Requires-Dist: inquirer<4.0.0,>=3.1.0
Requires-Dist: pydantic<3.0.0,>=2.0.0
Requires-Dist: rich<14.0.0,>=13.7.0
Requires-Dist: ruamel-yaml<0.19.0,>=0.18.5
Requires-Dist: typer<0.19.0,>=0.18.0
Provides-Extra: dev
Requires-Dist: black<24.0.0,>=23.12.0; extra == 'dev'
Requires-Dist: coverage[toml]<8.0.0,>=7.3.0; extra == 'dev'
Requires-Dist: mypy<2.0.0,>=1.8.0; extra == 'dev'
Requires-Dist: pre-commit<4.0.0,>=3.6.0; extra == 'dev'
Requires-Dist: pyinstaller<7.0.0,>=6.3.0; extra == 'dev'
Requires-Dist: pytest-asyncio<1.0.0,>=0.21.0; extra == 'dev'
Requires-Dist: pytest-cov<5.0.0,>=4.1.0; extra == 'dev'
Requires-Dist: pytest-mock<4.0.0,>=3.12.0; extra == 'dev'
Requires-Dist: pytest<8.0.0,>=7.4.3; extra == 'dev'
Requires-Dist: ruff<1.0.0,>=0.1.9; extra == 'dev'
